{"source":"toma","number":"singular","lemma":"tomar","lemmaPos":"verb","definitions":["Ato de tomar, pegar, segurar.","Ato de beber ou ingerir algo.","Ato de ocupar ou conquistar um lugar.","Ato de aceitar ou assumir uma responsabilidade.","Ato de receber algo."],"examples":["Ele toma o livro da mesa.","Ela toma um café todas as manhãs.","O exército toma a cidade.","Ele toma uma decisão importante.","A criança toma a vacina."],"synonyms":["pega","bebe","ocupa","assume","recebe"],"transcript":"ˈtoma"}