{"transcript":"viˈɔ.lɐ","exists":true,"definitions":["Instrumento musical de cordas, semelhante à guitarra mas geralmente com corpo mais pequeno e som distinto.","Instrumento de arco da família do violino, de tamanho médio e som mais grave que este.","Designação genérica para vários tipos de guitarras populares portuguesas."],"examples":["Ele toca viola numa banda de fado.","A viola d'arco tem um som aveludado.","Comprou uma viola braguesa em Braga."],"lemma":"viola","lemmaPos":"noun","synonyms":["guitarra","viola d'arco"],"number":"singular","pluralForm":"violas","gender":"feminine","source":"viola"}