{"transcript":"ẽ.pɾeʃ.ˈtaɾ","exists":true,"definitions":["Ceder algo a alguém por tempo limitado.","Dar ou facultar algo a outrem sob condição de restituição.","Atribuir ou comunicar uma qualidade."],"examples":["Podes emprestar-me o teu livro?","Ele vai emprestar o carro ao irmão.","O sol empresta brilho ao mar."],"lemma":"emprestar","lemmaPos":"verb","synonyms":["ceder","facilitar","conceder","dar"],"number":"singular","pastTenses":"emprestei, tinha emprestado","tense":"present","source":"emprestar"}