{"transcript":"ˈfɔɾ.mɐ","exists":true,"definitions":["Configuração externa de um corpo; feitio.","Recipiente onde se moldam substâncias ou se cozem alimentos.","Modo ou maneira de agir ou de se manifestar."],"examples":["A forma do vaso é elegante.","Colocou a massa na forma de bolo.","Não gostei da forma como ele falou."],"lemma":"forma","lemmaPos":"noun","synonyms":["formato","configuração","molde","maneira","modo"],"number":"singular","pluralForm":"formas","gender":"feminine","source":"forma"}